<?xml version="1.0" encoding="UTF-8"?>
<objects serializationModel="Studio.02.01.00">
	<object class="AudioFile" id="{bc34fec2-1578-4c69-8bee-d8c513a838eb}">
		<property name="assetPath">
			<value>FOLEY/dishes/fol_kitchen_dishes_07.wav</value>
		</property>
		<property name="frequencyInKHz">
			<value>44.0999985</value>
		</property>
		<property name="channelCount">
			<value>2</value>
		</property>
		<property name="length">
			<value>1.5</value>
		</property>
		<relationship name="masterAssetFolder">
			<destination>{2b2f03a5-63ff-41ad-9ede-036d8cd6b295}</destination>
		</relationship>
	</object>
</objects>
